{
  "pages": [
    {
      "path": "pages/tabBar/dashboard",
      "style": {
        "navigationBarTitleText": "OmniPanel",
        "navigationStyle": "default"
      }
    },
    {
      "path": "pages/tabBar/ai-assistant",
      "style": {
        "navigationBarTitleText": "AI Assistant",
        "navigationStyle": "default"
      }
    },
    {
      "path": "pages/tabBar/profile",
      "style": {
        "navigationBarTitleText": "Profile",
        "navigationStyle": "default"
      }
    }
  ],
  "globalStyle": {
    "navigationBarTextStyle": "white",
    "navigationBarTitleText": "OmniPanel",
    "navigationBarBackgroundColor": "#201d1d",
    "backgroundColor": "#201d1d"
  },
  "tabBar": {
    "custom": true,
    "color": "#9a9898",
    "selectedColor": "#007aff",
    "backgroundColor": "#1a1717",
    "borderStyle": "black",
    "list": [
      {
        "pagePath": "pages/tabBar/dashboard",
        "iconPath": "static/tabbar/dashboard.png",
        "selectedIconPath": "static/tabbar/dashboard-active.png",
        "text": "Dashboard"
      },
      {
        "pagePath": "pages/tabBar/ai-assistant",
        "iconPath": "static/tabbar/ai.png",
        "selectedIconPath": "static/tabbar/ai-active.png",
        "text": "AI"
      },
      {
        "pagePath": "pages/tabBar/profile",
        "iconPath": "static/tabbar/profile.png",
        "selectedIconPath": "static/tabbar/profile-active.png",
        "text": "Profile"
      }
    ]
  },
  "uniIdRouter": {}
}
